asciinema/__init__.py
asciinema/__main__.py
asciinema/api.py
asciinema/async_worker.py
asciinema/config.py
asciinema/file_writer.py
asciinema/http_adapter.py
asciinema/notifier.py
asciinema/player.py
asciinema/pty_.py
asciinema/recorder.py
asciinema/tty_.py
asciinema/urllib_http_adapter.py
asciinema/asciicast/__init__.py
asciinema/asciicast/events.py
asciinema/asciicast/raw.py
asciinema/asciicast/v1.py
asciinema/asciicast/v2.py
asciinema/commands/__init__.py
asciinema/commands/auth.py
asciinema/commands/cat.py
asciinema/commands/command.py
asciinema/commands/play.py
asciinema/commands/record.py
asciinema/commands/upload.py
asciinema/data/icon-256x256.png
asciinema-2.3.0.data/data/share/doc/asciinema/CHANGELOG.md
asciinema-2.3.0.data/data/share/doc/asciinema/CODE_OF_CONDUCT.md
asciinema-2.3.0.data/data/share/doc/asciinema/CONTRIBUTING.md
asciinema-2.3.0.data/data/share/doc/asciinema/README.md
asciinema-2.3.0.data/data/share/doc/asciinema/asciicast-v1.md
asciinema-2.3.0.data/data/share/doc/asciinema/asciicast-v2.md
asciinema-2.3.0.data/data/share/man/man1/asciinema.1
asciinema-2.3.0.dist-info/LICENSE
asciinema-2.3.0.dist-info/METADATA
asciinema-2.3.0.dist-info/WHEEL
asciinema-2.3.0.dist-info/entry_points.txt
asciinema-2.3.0.dist-info/top_level.txt
asciinema-2.3.0.dist-info/RECORD
