Metadata-Version: 2.1
Name: asciinema
Version: 2.3.0
Summary: Terminal session recorder
Home-page: https://asciinema.org
Download-URL: 
Author: Marcin Kulik
Author-email: m@ku1ik.com
License: GNU GPLv3
Classifier: Development Status :: 5 - Production/Stable
Classifier: Environment :: Console
Classifier: Intended Audience :: Developers
Classifier: Intended Audience :: System Administrators
Classifier: License :: OSI Approved :: GNU General Public License v3 or later (GPLv3+)
Classifier: Natural Language :: English
Classifier: Programming Language :: Python
Classifier: Programming Language :: Python :: 3.7
Classifier: Programming Language :: Python :: 3.8
Classifier: Programming Language :: Python :: 3.9
Classifier: Programming Language :: Python :: 3.10
Classifier: Programming Language :: Python :: 3.11
Classifier: Topic :: System :: Shells
Classifier: Topic :: Terminals
Classifier: Topic :: Utilities
License-File: LICENSE
